Tool.py
hjtestlib/__init__.py
hjtestlib/hjtest.py
hjtestlib-1.0.0.dist-info/METADATA
hjtestlib-1.0.0.dist-info/RECORD
hjtestlib-1.0.0.dist-info/WHEEL
hjtestlib-1.0.0.dist-info/top_level.txt
