Metadata-Version: 2.1
Name: hjtestlib
Version: 1.0.0
Summary: this is a hj lib
Home-page: https://www.baidu.com
Author: Hj
Author-email: 1573786811@qq.com
License: MIT
Platform: UNKNOWN
